invenio_config/__init__.py
invenio_config/default.py
invenio_config/entrypoint.py
invenio_config/env.py
invenio_config/folder.py
invenio_config/module.py
invenio_config/utils.py
invenio_config-1.1.0.dist-info/licenses/AUTHORS.rst
invenio_config-1.1.0.dist-info/licenses/LICENSE
invenio_config-1.1.0.dist-info/METADATA
invenio_config-1.1.0.dist-info/WHEEL
invenio_config-1.1.0.dist-info/top_level.txt
invenio_config-1.1.0.dist-info/RECORD
