Metadata-Version: 2.4
Name: invenio-config
Version: 1.1.0
Summary: "Invenio configuration loader."
Home-page: https://github.com/inveniosoftware/invenio-config
Author: CERN
Author-email: info@inveniosoftware.org
License: MIT
Keywords: invenio config
Platform: any
Classifier: Development Status :: 3 - Alpha
Requires-Python: >=3.7
License-File: LICENSE
License-File: AUTHORS.rst
Requires-Dist: Flask>=0.11.1
Requires-Dist: invenio-base<3.0.0,>=2.3.0
Provides-Extra: tests
Requires-Dist: pytest-black-ng>=0.4.0; extra == "tests"
Requires-Dist: pytest-invenio<3.0.0,>=2.1.0; extra == "tests"
Requires-Dist: mock>=2.0.0; extra == "tests"
Requires-Dist: Sphinx>=1.8.0; extra == "tests"
Dynamic: license-file
